CustomCommands/Commands.py
CustomCommands/__init__.py
CustomCommands-1.0.dist-info/METADATA
CustomCommands-1.0.dist-info/WHEEL
CustomCommands-1.0.dist-info/top_level.txt
CustomCommands-1.0.dist-info/RECORD
