Metadata-Version: 2.1
Name: CustomCommands
Version: 1.0
Summary: Discord Bot Custom Commands
Home-page: https://github.com/AOStormDev/Discord-Custom-Commands
Author: DevStorm
Author-email: storm@stormdev.club
License: UNKNOWN
Platform: UNKNOWN
Classifier: Programming Language :: Python :: 3
Classifier: License :: OSI Approved :: MIT License
